{
    "os": "Linux-6.5.0-25-generic-x86_64-with-glibc2.35",
    "python": "3.11.7",
    "heartbeatAt": "2024-03-19T14:37:28.924630",
    "startedAt": "2024-03-19T14:37:24.411972",
    "docker": null,
    "cuda": null,
    "args": [],
    "state": "running",
    "program": "q2.ipynb",
    "codePathLocal": "q2.ipynb",
    "root": "/home/srihari/SEM6/CV/CV_A2",
    "git": {
        "remote": "https://github.com/sriharib128/CV_A2.git",
        "commit": "dfaa0e2f4403985b52b28f407f4d707bdd168385"
    },
    "email": "sriharib128",
    "host": "srihari-ubuntu",
    "username": "srihari",
    "executable": "/home/srihari/miniconda3/envs/conda_cv/bin/python",
    "cpu_count": 10,
    "cpu_count_logical": 12,
    "cpu_freq": {
        "current": 1.173416666666667,
        "min": 400.0,
        "max": 3900.0
    },
    "cpu_freq_per_core": [
        {
            "current": 0.505,
            "min": 400.0,
            "max": 4700.0
        },
        {
            "current": 0.418,
            "min": 400.0,
            "max": 4700.0
        },
        {
            "current": 0.696,
            "min": 400.0,
            "max": 4700.0
        },
        {
            "current": 0.4,
            "min": 400.0,
            "max": 4700.0
        },
        {
            "current": 1.702,
            "min": 400.0,
            "max": 3500.0
        },
        {
            "current": 1.664,
            "min": 400.0,
            "max": 3500.0
        },
        {
            "current": 1.707,
            "min": 400.0,
            "max": 3500.0
        },
        {
            "current": 1.715,
            "min": 400.0,
            "max": 3500.0
        },
        {
            "current": 0.4,
            "min": 400.0,
            "max": 3500.0
        },
        {
            "current": 0.876,
            "min": 400.0,
            "max": 3500.0
        },
        {
            "current": 0.4,
            "min": 400.0,
            "max": 3500.0
        },
        {
            "current": 0.4,
            "min": 400.0,
            "max": 3500.0
        }
    ],
    "disk": {
        "/": {
            "total": 258.4741439819336,
            "used": 218.03556442260742
        }
    },
    "memory": {
        "total": 15.302440643310547
    }
}
